setup.py
funniest_ltp/__init__.py
funniest_ltp.egg-info/PKG-INFO
funniest_ltp.egg-info/SOURCES.txt
funniest_ltp.egg-info/dependency_links.txt
funniest_ltp.egg-info/not-zip-safe
funniest_ltp.egg-info/top_level.txt