Metadata-Version: 1.0
Name: funniest-ltp
Version: 0.1
Summary: blablabla
Home-page: http://github.com/storborg/funniest
Author: Flying Circus
Author-email: flyingcircus@example.com
License: LTP
Platform: UNKNOWN
